how_much/__init__.py
how_much/cli.py
how_much/ignore.py
how_much/main.py
how_much/stats/__init__.py
how_much/stats/base_stat.py
how_much/stats/comment_stats.py
how_much/stats/core_stats.py
how_much/stats/file_counter.py
how_much_repo_analyzer-0.1.0.dist-info/entry_points.txt
how_much_repo_analyzer-0.1.0.dist-info/LICENSE
how_much_repo_analyzer-0.1.0.dist-info/METADATA
how_much_repo_analyzer-0.1.0.dist-info/WHEEL
how_much_repo_analyzer-0.1.0.dist-info/RECORD
