Metadata-Version: 2.3
Name: how-much-repo-analyzer
Version: 0.1.0
Summary: A command-line tool to calculate statistics for a code repository, ignoring files from .gitignore and .howmuchignore.
License: MIT
Author: Rahmat Ansari
Author-email: rahmat.ansari.dev@gmail.com
Requires-Python: >=3.8,<4.0
Classifier: License :: OSI Approved :: MIT License
Classifier: Programming Language :: Python :: 3
Classifier: Programming Language :: Python :: 3.8
Classifier: Programming Language :: Python :: 3.9
Classifier: Programming Language :: Python :: 3.10
Classifier: Programming Language :: Python :: 3.11
Classifier: Programming Language :: Python :: 3.12
Classifier: Programming Language :: Python :: 3.13
Requires-Dist: rich (>=13.7.1,<14.0.0)
Requires-Dist: typer[all] (>=0.12.3,<0.13.0)
Project-URL: Homepage, https://github.com/Rahmat-JS/how-much
Project-URL: Repository, https://github.com/Rahmat-JS/how-much
